setup.py
CubixOCR_Trainer/__init__.py
CubixOCR_Trainer/cubix_ocr_trainer.py
cubix_ocr_trainer.egg-info/PKG-INFO
cubix_ocr_trainer.egg-info/SOURCES.txt
cubix_ocr_trainer.egg-info/dependency_links.txt
cubix_ocr_trainer.egg-info/not-zip-safe
cubix_ocr_trainer.egg-info/top_level.txt