Metadata-Version: 1.1
Name: cubix-ocr-trainer
Version: 1.0
Summary: Use of Tesserect OCR Training Process
Home-page: https://github.com/RafiAfridiCubix/TesserectOCR
Author: Rafi Ullah Afridi
Author-email: rafiullah.khan@cubixlabs.com
License: None
Download-URL: https://github.com/RafiAfridiCubix/TesserectOCR.git
Keywords: tesserect ocr training,tesserect ocr,ocr training
Platform: UNKNOWN
